ilio/__init__.py
ilio-0.4.0.dist-info/DESCRIPTION.rst
ilio-0.4.0.dist-info/METADATA
ilio-0.4.0.dist-info/RECORD
ilio-0.4.0.dist-info/WHEEL
ilio-0.4.0.dist-info/metadata.json
ilio-0.4.0.dist-info/top_level.txt
